<BackupInst xmlns="http://www.microsoft.com/GroupPolicy/GPOOperations/Manifest"><GPOGuid><![CDATA[{EFEC799A-3E5D-4701-AF51-E29DFD504E99}]]></GPOGuid><GPODomain><![CDATA[Firebolt21.Local]]></GPODomain><GPODomainGuid><![CDATA[{0d694c8b-ab1f-464a-8d1e-7f308e89a099}]]></GPODomainGuid><GPODomainController><![CDATA[FB-213-20.Firebolt21.Local]]></GPODomainController><BackupTime><![CDATA[2025-02-11T08:45:21]]></BackupTime><ID><![CDATA[{3D7CB2B2-AF83-4146-8A70-D04CFED640A3}]]></ID><Comment><![CDATA[]]></Comment><GPODisplayName><![CDATA[DC Local Policy]]></GPODisplayName></BackupInst>
